{"is_source_file": true, "format": "TypeScript/TSX", "description": "This file defines a React component for a page that allows users to invoke external tools via a proxy UI. It manages form inputs for provider, tool, tenant ID, connector ID, and arguments, and displays the results or errors. The code includes hooks for state management and a function to call an API endpoint.", "external_files": ["@/lib/api", "@/components/common/Feedback"], "external_methods": ["invokeTool"], "published": [], "classes": [], "methods": [{"name": "run", "description": "Handles invoking the external tool API with user-provided parameters, manages loading and error state, and updates the result upon completion."}], "calls": ["invokeTool(payload)"], "search-terms": ["ToolsPage", "invokeTool", "ToolsPage React component", "page.tsx", "useState hooks", "tool invocation UI"], "state": 2, "file_id": 19, "knowledge_revision": 64, "git_revision": "", "revision_history": [{"43": ""}, {"64": ""}], "ctags": [], "hash": "f1968a251856636e7c41bc9a30cd847d", "format-version": 4, "code-base-name": "frontend_app", "filename": "frontend_app/src/app/tools/page.tsx"}